uipath_connectors/sap_odata/__init__.py
uipath_connectors/sap_odata/client.py
uipath_connectors/sap_odata/errors.py
uipath_connectors/sap_odata/py.typed
uipath_connectors/sap_odata/types.py
uipath_connectors/sap_odata/api/__init__.py
uipath_connectors/sap_odata/api/entity/__init__.py
uipath_connectors/sap_odata/api/entity/list_all_entity_records.py
uipath_connectors/sap_odata/models/__init__.py
uipath_connectors/sap_odata/models/default_error.py
uipath_connectors_sap_odata-1.0.25.dev12.dist-info/METADATA
uipath_connectors_sap_odata-1.0.25.dev12.dist-info/WHEEL
uipath_connectors_sap_odata-1.0.25.dev12.dist-info/entry_points.txt
uipath_connectors_sap_odata-1.0.25.dev12.dist-info/top_level.txt
uipath_connectors_sap_odata-1.0.25.dev12.dist-info/RECORD
